{
  "typeCheckingMode": "basic", // basic to ease transition, this entire config is (automatically copypasted and) to be adapted to each project
  "reportAny": false,
  "reportImplicitOverride": false,
  // cause typing.override leads to false positives
  "reportMissingSuperCall": false,
  "reportMissingParameterType": false, // already done by ruff
  "reportUnusedCallResult": false, // gibt schlimmeres!
  "reportPrivateUsage": false, // underscore convention is enough!
  "reportIncompatibleMethodOverride": false,
  "reportMissingTypeStubs": false,
  "reportUnknownLambdaType": false, // seems to affect all lambdas


  "reportUnknownVariableType": "warning",
  "reportUnknownMemberType": "warning",
  "reportUnknownArgumentType": "warning",
  "reportMissingTypeArgument": "warning",
  "reportUnknownParameterType": "warning",
  "reportUnusedVariable": "warning",
    "exclude": [
      "**/___*",
      "tests"
  ]
}